{
    "configurations": [
        {
            "name": "Win32",
            "includePath": [
                "C:\\Users\\Alex\\AppData\\Local\\Arduino15\\packages\\arduino\\tools\\**",
                "C:\\Users\\Alex\\Documents\\Arduino\\libraries\\MySensors\\**",
                "C:\\Users\\Alex\\AppData\\Local\\Arduino15\\packages\\arduino\\hardware\\avr\\1.8.3\\**",
                "${workspaceRoot}\\**"
            ],
            "browse": {
                "limitSymbolsToIncludedHeaders": false,
                "path": [
                    "${workspaceFolder}\\**",
                    "C:\\Users\\Alex\\Documents\\Arduino\\libraries\\MySensors\\**",
                    "C:\\Users\\Alex\\Documents\\Arduino\\libraries\\DallasTemperature\\**",
                    "C:\\Users\\Alex\\Documents\\Arduino\\libraries\\OneWire\\**",
                    "C:\\Users\\Alex\\Documents\\Arduino\\libraries\\myIncludes\\**",
                    "C:\\Users\\Alex\\Documents\\Arduino\\libraries\\Time\\**",
                    "${workspaceRoot}\\**"
                ]
            },
            "forcedInclude": [
                "C:\\Users\\Alex\\AppData\\Local\\Arduino15\\packages\\arduino\\hardware\\avr\\1.8.3\\cores\\arduino\\Arduino.h"
            ],
            "intelliSenseMode": "msvc-x64",
            "compilerPath": "C:/Program Files (x86)/Microsoft Visual Studio/2019/Community/VC/Tools/MSVC/14.24.28314/bin/Hostx64/x64/cl.exe",
            "cStandard": "c11",
            "cppStandard": "c++17"
        }
    ],
    "version": 4
}